cronflow/__init__.py
cronflow/cron_switch.py
cronflow-0.2.dist-info/licenses/LICENSE
cronflow-0.2.dist-info/METADATA
cronflow-0.2.dist-info/WHEEL
cronflow-0.2.dist-info/top_level.txt
cronflow-0.2.dist-info/RECORD
