Metadata-Version: 2.4
Name: cronflow
Version: 0.2
Summary: A Python package for controlling cron job execution
Home-page: https://github.com/jinwenliu/cronflow
Author: Xileven
Author-email: hi@bringyouhome.org
Keywords: cron,scheduling,job control,automation
Classifier: Programming Language :: Python :: 3.9
Classifier: Programming Language :: Python :: 3.10
Classifier: Programming Language :: Python :: 3.11
Classifier: Programming Language :: Python :: 3.12
Classifier: License :: OSI Approved :: MIT License
Classifier: Operating System :: OS Independent
Classifier: Topic :: System :: Systems Administration
Classifier: Topic :: Utilities
Requires-Python: >=3.9
License-File: LICENSE
Dynamic: author
Dynamic: author-email
Dynamic: classifier
Dynamic: description
Dynamic: description-content-type
Dynamic: home-page
Dynamic: keywords
Dynamic: license-file
Dynamic: requires-python
Dynamic: summary
